.gitignore
COPYING.txt
README.txt
gitlsfiles.py
setup.py
gitlsfiles.egg-info/PKG-INFO
gitlsfiles.egg-info/SOURCES.txt
gitlsfiles.egg-info/dependency_links.txt
gitlsfiles.egg-info/entry_points.txt
gitlsfiles.egg-info/top_level.txt
