Metadata-Version: 1.0
Name: gitlsfiles
Version: 0.1.1
Summary: setuptools integration for Git
Home-page: UNKNOWN
Author: Yannick Gingras
Author-email: ygingras@ygingras.net
License: GPL v3 or later
Platform: UNKNOWN
Classifier: Topic :: Software Development :: Version Control
